datawise/__init__.py
datawise/exceptions.py
datawise-0.0.23.dist-info/LICENSE
datawise-0.0.23.dist-info/METADATA
datawise-0.0.23.dist-info/WHEEL
datawise-0.0.23.dist-info/RECORD
