Metadata-Version: 2.1
Name: datawise
Version: 0.0.23
Summary: AI Assistant for Python Data Analytics
Author: DataWise Team
Requires-Python: >=3.9.0,<4.0.0
Classifier: Programming Language :: Python :: 3
Classifier: Programming Language :: Python :: 3.9
Classifier: Programming Language :: Python :: 3.10
Classifier: Programming Language :: Python :: 3.11
Requires-Dist: python-dotenv (>=1.0.0,<2.0.0)
Requires-Dist: requests (==2.31.0)
Requires-Dist: retry (>=0.9.2,<0.10.0)
Requires-Dist: urllib3 (>=1.26.6,<2.0.0)
